setup.py
ASS/__init__.py
test/test.py
zddf.egg-info/PKG-INFO
zddf.egg-info/SOURCES.txt
zddf.egg-info/dependency_links.txt
zddf.egg-info/top_level.txt