Metadata-Version: 2.1
Name: zddf
Version: 2.0
Summary: 自动打分
Author: keyee
Author-email: du1872779171@163.com
License: UNKNOWN
Platform: UNKNOWN
